{
  "context": {
    "networkId": "nfh.global/testnet-deg",
    "version": "2.0.0",
    "action": "discover",
    "bapId": "bap.example.com",
    "bapUri": "http://beckn-router:9000/bap/receiver",
    "transactionId": "txn-p2p-001",
    "messageId": "msg-discover-001",
    "timestamp": "2026-04-25T09:00:00Z"
  },
  "message": {
    "intent": {
      "filters": {
        "type": "jsonpath",
        "expression": "$.catalogs[*].offers[*][?(@.offerAttributes['@type']=='EnergyTradeOffer')]"
      }
    }
  }
}
